{
  "url": "https://api.github.com/repos/nmhjklnm/cueapp/releases/277824833",
  "assets_url": "https://api.github.com/repos/nmhjklnm/cueapp/releases/277824833/assets",
  "upload_url": "https://uploads.github.com/repos/nmhjklnm/cueapp/releases/277824833/assets{?name,label}",
  "html_url": "https://github.com/nmhjklnm/cueapp/releases/tag/v0.1.0",
  "id": 277824833,
  "author": {
    "login": "github-actions[bot]",
    "id": 41898282,
    "node_id": "MDM6Qm90NDE4OTgyODI=",
    "avatar_url": "https://avatars.githubusercontent.com/in/15368?v=4",
    "gravatar_id": "",
    "url": "https://api.github.com/users/github-actions%5Bbot%5D",
    "html_url": "https://github.com/apps/github-actions",
    "followers_url": "https://api.github.com/users/github-actions%5Bbot%5D/followers",
    "following_url": "https://api.github.com/users/github-actions%5Bbot%5D/following{/other_user}",
    "gists_url": "https://api.github.com/users/github-actions%5Bbot%5D/gists{/gist_id}",
    "starred_url": "https://api.github.com/users/github-actions%5Bbot%5D/starred{/owner}{/repo}",
    "subscriptions_url": "https://api.github.com/users/github-actions%5Bbot%5D/subscriptions",
    "organizations_url": "https://api.github.com/users/github-actions%5Bbot%5D/orgs",
    "repos_url": "https://api.github.com/users/github-actions%5Bbot%5D/repos",
    "events_url": "https://api.github.com/users/github-actions%5Bbot%5D/events{/privacy}",
    "received_events_url": "https://api.github.com/users/github-actions%5Bbot%5D/received_events",
    "type": "Bot",
    "user_view_type": "public",
    "site_admin": false
  },
  "node_id": "RE_kwDOQ8R6Jc4Qj0VB",
  "tag_name": "v0.1.0",
  "target_commitish": "main",
  "name": "v0.1.0",
  "draft": false,
  "immutable": false,
  "prerelease": false,
  "created_at": "2026-01-19T07:29:04Z",
  "updated_at": "2026-01-19T07:33:24Z",
  "published_at": "2026-01-19T07:33:24Z",
  "assets": [
    {
      "url": "https://api.github.com/repos/nmhjklnm/cueapp/releases/assets/342642601",
      "id": 342642601,
      "node_id": "RA_kwDOQ8R6Jc4UbE-p",
      "name": "cueapp-0.1.0-arm64-mac.zip",
      "label": "",
      "uploader": {
        "login": "github-actions[bot]",
        "id": 41898282,
        "node_id": "MDM6Qm90NDE4OTgyODI=",
        "avatar_url": "https://avatars.githubusercontent.com/in/15368?v=4",
        "gravatar_id": "",
        "url": "https://api.github.com/users/github-actions%5Bbot%5D",
        "html_url": "https://github.com/apps/github-actions",
        "followers_url": "https://api.github.com/users/github-actions%5Bbot%5D/followers",
        "following_url": "https://api.github.com/users/github-actions%5Bbot%5D/following{/other_user}",
        "gists_url": "https://api.github.com/users/github-actions%5Bbot%5D/gists{/gist_id}",
        "starred_url": "https://api.github.com/users/github-actions%5Bbot%5D/starred{/owner}{/repo}",
        "subscriptions_url": "https://api.github.com/users/github-actions%5Bbot%5D/subscriptions",
        "organizations_url": "https://api.github.com/users/github-actions%5Bbot%5D/orgs",
        "repos_url": "https://api.github.com/users/github-actions%5Bbot%5D/repos",
        "events_url": "https://api.github.com/users/github-actions%5Bbot%5D/events{/privacy}",
        "received_events_url": "https://api.github.com/users/github-actions%5Bbot%5D/received_events",
        "type": "Bot",
        "user_view_type": "public",
        "site_admin": false
      },
      "content_type": "application/zip",
      "state": "uploaded",
      "size": 121167228,
      "digest": "sha256:b8c20432518ea4768e07bfe4cf6a2633039b95c3d8ac3a5cd1f47b8e8ec43ea1",
      "download_count": 0,
      "created_at": "2026-01-19T07:33:17Z",
      "updated_at": "2026-01-19T07:33:23Z",
      "browser_download_url": "https://github.com/nmhjklnm/cueapp/releases/download/v0.1.0/cueapp-0.1.0-arm64-mac.zip"
    }
  ],
  "tarball_url": "https://api.github.com/repos/nmhjklnm/cueapp/tarball/v0.1.0",
  "zipball_url": "https://api.github.com/repos/nmhjklnm/cueapp/zipball/v0.1.0",
  "body": "**Full Changelog**: https://github.com/nmhjklnm/cueapp/commits/v0.1.0"
}
